combinatorial_config/__init__.py
combinatorial_config/generate_combinations.py
combinatorial_config/test_generate_combinations.py
combinatorial_config/normalizers/__init__.py
combinatorial_config/normalizers/range.py
combinatorial_config/normalizers/test_range.py
combinatorial_config/schemas/__init__.py
combinatorial_config/schemas/_undefined_type.py
combinatorial_config/schemas/combinatorial_object.py
combinatorial_config/schemas/dataclass_protocol.py
combinatorial_config/schemas/enum_field.py
combinatorial_config/schemas/enumerable_value.py
combinatorial_config/schemas/normalized_range_field.py
combinatorial_config/schemas/number_value.py
combinatorial_config/schemas/primitive_value.py
combinatorial_config/schemas/range_field.py
combinatorial_config/schemas/test_undefined.py
combinatorial_config/schemas/undefined.py
combinatorial_config/validators/__init__.py
combinatorial_config/validators/is_combinatorial_object.py
combinatorial_config/validators/is_enum_field.py
combinatorial_config/validators/is_enumerable_value.py
combinatorial_config/validators/is_number_value.py
combinatorial_config/validators/is_primitive_value.py
combinatorial_config/validators/is_range_field.py
combinatorial_config/validators/is_undefined.py
combinatorial_config/validators/test_is_combinatorial_object.py
combinatorial_config/validators/test_is_enum_field.py
combinatorial_config/validators/test_is_enumerable_value.py
combinatorial_config/validators/test_is_number_value.py
combinatorial_config/validators/test_is_primitive_value.py
combinatorial_config/validators/test_is_range_field.py
combinatorial_config/validators/test_is_undefined.py
combinatorial_config-0.2.2.dist-info/METADATA
combinatorial_config-0.2.2.dist-info/WHEEL
combinatorial_config-0.2.2.dist-info/licenses/LICENSE
combinatorial_config-0.2.2.dist-info/RECORD
