Metadata-Version: 2.4
Name: combinatorial-config
Version: 0.2.2
Summary: Add your description here
Author-email: devcomfort <im@devcomfort.me>
License-File: LICENSE
Requires-Python: >=3.8
Requires-Dist: toolz>=1.1.0
